<BackupInst xmlns="http://www.microsoft.com/GroupPolicy/GPOOperations/Manifest"><GPOGuid><![CDATA[{709679C5-D2E3-4E1C-9CA0-9431AEC282DB}]]></GPOGuid><GPODomain><![CDATA[prccdc.htb]]></GPODomain><GPODomainGuid><![CDATA[{146c4c06-3ccf-47a5-b92b-e7cef89ab47f}]]></GPODomainGuid><GPODomainController><![CDATA[dc.prccdc.htb]]></GPODomainController><BackupTime><![CDATA[2026-01-24T21:16:27]]></BackupTime><ID><![CDATA[{20A98617-57A4-4786-A9C6-0A791BD7D285}]]></ID><Comment><![CDATA[]]></Comment><GPODisplayName><![CDATA[Databases Firewall Policy]]></GPODisplayName></BackupInst>
